williamarsecond/__init__.py
williamarsecond/hello.py
williamarsecond-0.0.1.dist-info/LICENSE
williamarsecond-0.0.1.dist-info/METADATA
williamarsecond-0.0.1.dist-info/WHEEL
williamarsecond-0.0.1.dist-info/top_level.txt
williamarsecond-0.0.1.dist-info/RECORD
