Metadata-Version: 2.1
Name: williamarsecond
Version: 0.0.1
Summary: A basic hello package sdaasdasdasdsad
Author: William Arsenault
Author-email: idk@gmail.com
License: UNKNOWN
Keywords: python
Platform: UNKNOWN
Classifier: Development Status :: 1 - Planning
Classifier: Intended Audience :: Developers
Classifier: Programming Language :: Python :: 3
Classifier: Operating System :: Unix
Classifier: Operating System :: MacOS :: MacOS X
Classifier: Operating System :: Microsoft :: Windows
License-File: LICENSE
